readwise_to_datasette/__init__.py
readwise_to_datasette-0.2.0.dist-info/METADATA
readwise_to_datasette-0.2.0.dist-info/WHEEL
readwise_to_datasette-0.2.0.dist-info/entry_points.txt
readwise_to_datasette-0.2.0.dist-info/RECORD
